swapdate/__init__.py
swapdate/swapdate.py
swapdate-0.4.dist-info/DESCRIPTION.rst
swapdate-0.4.dist-info/METADATA
swapdate-0.4.dist-info/RECORD
swapdate-0.4.dist-info/WHEEL
swapdate-0.4.dist-info/metadata.json
swapdate-0.4.dist-info/top_level.txt
