Metadata-Version: 2.0
Name: swapdate
Version: 0.4
Summary: Swap the current date from one format into different format
Home-page: https://github.com/jvlingam/swapdate
Author: Vijay Lingam
Author-email: jvlingam@gmail.com
License: VijayLingam
Platform: All
